streaming_package/__init__.py
streaming_package/object_oriented_script.py
streamdata-0.1.0.dist-info/License.txt
streamdata-0.1.0.dist-info/METADATA
streamdata-0.1.0.dist-info/WHEEL
streamdata-0.1.0.dist-info/top_level.txt
streamdata-0.1.0.dist-info/RECORD
